safeGPT/__init__.py
safeGPT/abstraction.py
safeGPT/handlers.py
safeGPT/main.py
safeGPT/rules.py
tests/__init__.py
tests/test_main.py
tests/test_rule.py
safeGPT-0.0.1.dist-info/LICENSE
safeGPT-0.0.1.dist-info/METADATA
safeGPT-0.0.1.dist-info/WHEEL
safeGPT-0.0.1.dist-info/top_level.txt
safeGPT-0.0.1.dist-info/RECORD
