Metadata-Version: 2.1
Name: safeGPT
Version: 0.0.1
Summary: A safer way to use GPT chat models
Home-page: https://github.com/Baicheng-MiQ/safeGPT
Requires-Python: >=3.10
License-File: LICENSE
Requires-Dist: openai (>=0.27.0)
